db/MySQL.py
db/__init__.py
qky_tools/__init__.py
qky_tools/db_tools/MySQL.py
qky_tools/db_tools/__init__.py
qky_tools/req_tools/__init__.py
qky_tools/req_tools/cacheReq.py
qky_tools/req_tools/proxyReq.py
qky_tools/str_tools/__init__.py
qky_tools/str_tools/chinese_tools.py
req/__init__.py
req/cacheReq.py
req/proxy.py
qky_tools-0.6.1.dist-info/LICENSE.txt
qky_tools-0.6.1.dist-info/METADATA
qky_tools-0.6.1.dist-info/WHEEL
qky_tools-0.6.1.dist-info/top_level.txt
qky_tools-0.6.1.dist-info/RECORD
