Metadata-Version: 2.1
Name: qky-tools
Version: 0.6.1
Summary: python tools collection
Home-page: https://github.com/qiaokuoyuan/py-tools
Author: qiaokuoyuan
Author-email: 457361577@qq.com
License: MIT
Platform: UNKNOWN
Classifier: License :: OSI Approved :: MIT License
Classifier: Programming Language :: Python
Classifier: Programming Language :: Python :: 3
Classifier: Programming Language :: Python :: 3.6
Classifier: Programming Language :: Python :: Implementation :: CPython
Classifier: Programming Language :: Python :: Implementation :: PyPy
Requires-Python: >=3.6.0
License-File: LICENSE.txt
Requires-Dist: pymysql
Requires-Dist: nanoid
Requires-Dist: cachetools
